sp_calculator/__init__.py
sp_calculator/test__init__.py
sp_calculator-0.2.2.dist-info/LICENSE
sp_calculator-0.2.2.dist-info/WHEEL
sp_calculator-0.2.2.dist-info/METADATA
sp_calculator-0.2.2.dist-info/RECORD
