Metadata-Version: 2.1
Name: sp_calculator
Version: 0.2.2
Summary: A basic dependency-free calculator module
Author-email: Seb <sebastianpikand@gmail.com>
Classifier: License :: OSI Approved :: MIT License
Project-URL: Home, https://github.com/sebastianpikand/sp_calculator
